dag_simple/__init__.py
dag_simple/context.py
dag_simple/dag.py
dag_simple/exceptions.py
dag_simple/execution.py
dag_simple/introspection.py
dag_simple/node.py
dag_simple/py.typed
dag_simple/validation.py
dag_simple-0.3.0.dist-info/METADATA
dag_simple-0.3.0.dist-info/WHEEL
dag_simple-0.3.0.dist-info/licenses/LICENSE
dag_simple-0.3.0.dist-info/RECORD
