Metadata-Version: 2.4
Name: dag-simple
Version: 0.3.0
Summary: A dead simple, type-safe DAG (Directed Acyclic Graph) library with runtime validation, caching, and async support
Project-URL: Homepage, https://github.com/Apex-Engineers-Inc/dag_simple
Project-URL: Documentation, https://github.com/Apex-Engineers-Inc/dag_simple#readme
Project-URL: Repository, https://github.com/Apex-Engineers-Inc/dag_simple
Project-URL: Bug Tracker, https://github.com/Apex-Engineers-Inc/dag_simple/issues
Author: Apex Engineers, Inc.
License: MIT
License-File: LICENSE
Keywords: async,asyncio,caching,dag,directed-acyclic-graph,pipeline,type-safe,validation,workflow
Classifier: Development Status :: 4 - Beta
Classifier: Intended Audience :: Developers
Classifier: License :: OSI Approved :: MIT License
Classifier: Programming Language :: Python :: 3
Classifier: Programming Language :: Python :: 3.10
Classifier: Programming Language :: Python :: 3.11
Classifier: Programming Language :: Python :: 3.12
Classifier: Programming Language :: Python :: 3.13
Classifier: Programming Language :: Python :: 3.14
Classifier: Topic :: Software Development :: Libraries
Classifier: Topic :: Software Development :: Libraries :: Python Modules
Classifier: Typing :: Typed
Requires-Python: >=3.10
Provides-Extra: dev
Requires-Dist: coverage[toml]>=7.0.0; extra == 'dev'
Requires-Dist: pyright>=1.1.350; extra == 'dev'
Requires-Dist: ruff>=0.2.0; extra == 'dev'
Requires-Dist: rustest>=0.4.0; extra == 'dev'
